{
    "parameters": {
        "workspaceId": "f089354e-8366-4e18-aea3-4cb4a3a50b48",
        "environmentId": "41ce06d1-d81b-4ea0-bc6d-2ce3dd2f8e87"
    },
    "responses": {
        "200": {
            "body": {
                "publishDetails": {
                    "state": "Cancelled",
                    "targetVersion": "d9d95b01-248f-4ef4-bd7e-9d3f1f6447be",
                    "startTime": "2024-03-29T15:00:33.4359355Z",
                    "endTime": "2024-03-29T15:00:47.1407904Z",
                    "componentPublishInfo": {
                        "sparkLibraries": {
                            "state": "Cancelled"
                        },
                        "sparkSettings": {
                            "state": "Cancelled"
                        }
                    }
                }
            }
        }
    }
}